{
  "uuid": "bdd7ad43-f0fc-4716-90c1-87454c40dd95",
  "parentName": "EntityDefinition",
  "parentUuid": "54b9c72f-d4f3-4db9-9e0e-0dc840b530bd",
  "parentDefinitionVersionUuid": "bdd7ad43-f0fc-4716-90c1-87454c40dd95",
  "entityUuid": "54b9c72f-d4f3-4db9-9e0e-0dc840b530bd",
  "name": "EntityDefinition",
  "conceptLevel": "MetaModel",
  "description": "definition of an entity",
  "defaultInstanceDetailsReportUuid": "acd55b04-84df-427e-b219-cf0e01a6881b",
  "viewAttributes": [
    "name",
    "description",
    "entityUuid",
    "viewAttributes",
    "uuid"
  ],
  "jzodSchema": {
    "type": "object",
    "definition": {
      "uuid": {
        "type": "uuid",
        "tag": {
          "value": {
            "id": 1,
            "defaultLabel": "Uuid",
            "editable": false
          }
        }
      },
      "parentName": {
        "type": "string",
        "tag": {
          "value": {
            "id": 2,
            "defaultLabel": "Entity Name",
            "editable": false
          }
        }
      },
      "parentUuid": {
        "type": "uuid",
        "tag": {
          "value": {
            "id": 3,
            "defaultLabel": "Entity Uuid",
            "editable": false
          }
        }
      },
      "parentDefinitionVersionUuid": {
        "type": "uuid",
        "optional": true,
        "tag": {
          "value": {
            "id": 4,
            "defaultLabel": "Entity Definition Version Uuid",
            "editable": false
          }
        }
      },
      "name": {
        "type": "string",
        "tag": {
          "value": {
            "id": 5,
            "defaultLabel": "Name",
            "editable": false
          }
        }
      },
      "entityUuid": {
        "type": "uuid",
        "tag": {
          "value": {
            "id": 6,
            "defaultLabel": "Entity Uuid of the Entity which this definition is the definition",
            "editable": false
          }
        }
      },
      "conceptLevel": {
        "type": "enum",
        "definition": [
          "MetaModel",
          "Model",
          "Data"
        ],
        "optional": true,
        "tag": {
          "value": {
            "id": 7,
            "defaultLabel": "Concept Level",
            "editable": false
          }
        }
      },
      "description": {
        "type": "string",
        "optional": true,
        "tag": {
          "value": {
            "id": 8,
            "defaultLabel": "Description",
            "editable": true
          }
        }
      },
      "defaultInstanceDetailsReportUuid": {
        "type": "uuid",
        "optional": true,
        "tag": {
          "value": {
            "id": 9,
            "defaultLabel": "Default Report used to display instances of this Entity",
            "editable": false,
            "selectorParams": {
              "targetEntity": "3f2baa83-3ef7-45ce-82ea-6a43f7a8c916",
              "targetEntityApplicationSection": "model",
              "targetEntityOrderInstancesBy": "name"
            }
          }
        }
      },
      "viewAttributes": {
        "type": "array",
        "optional": true,
        "definition": {
          "type": "string"
        },
        "tag": {
          "value": {
            "id": 10,
            "editable": true
          }
        }
      },
      "icon": {
        "type": "schemaReference",
        "optional": true,
        "definition": {
          "absolutePath": "fe9b7d99-f216-44de-bb6e-60e1a1ebb739",
          "relativePath": "miroirIcon"
        }
      },
      "display": {
        "type": "object",
        "optional": true,
        "tag": {
          "value": {
            "id": 13,
            "defaultLabel": "Display Options",
            "editable": true
          }
        },
        "definition": {
          "foldSubLevels": {
            "type": "record",
            "optional": true,
            "tag": {
              "value": {
                "defaultLabel": "Unfold Sub Levels",
                "editable": true
              }
            },
            "definition": {
              "type": "boolean"
            }
          }
        }
      },
      "jzodSchema": {
        "type": "schemaReference",
        "definition": {
          "absolutePath": "fe9b7d99-f216-44de-bb6e-60e1a1ebb739",
          "relativePath": "jzodObject"
        },
        "tag": {
          "value": {
            "id": 12,
            "defaultLabel": "Jzod Schema",
            "editable": true
          }
        }
      }
    }
  }
}